cmdlinker/__init__.py
cmdlinker/analyse.py
cmdlinker/builtin/__init__.py
cmdlinker/builtin/cmd_conf.py
cmdlinker/builtin/exception.py
cmdlinker/builtin/file_operation.py
cmdlinker/builtin/logger_operation.py
cmdlinker/builtin/module_template.py.j2
cmdlinker/builtin/shell_utils.py
cmdlinker/builtin/ssh_utils.py
cmdlinker/cli.yaml
cmdlinker/client.py
cmdlinker/const.py
cmdlinker/model/__init__.py
cmdlinker/model/models.py
cmdlinker-0.1.4.dist-info/entry_points.txt
cmdlinker-0.1.4.dist-info/LICENSE
cmdlinker-0.1.4.dist-info/METADATA
cmdlinker-0.1.4.dist-info/WHEEL
cmdlinker-0.1.4.dist-info/RECORD
