Metadata-Version: 2.1
Name: cmdlinker
Version: 0.1.4
Summary: 用于解析命令/执行命令，将命令解析成py对象，在进行命令操作时，直接操作命令对象即可，可用于命令自动化测试，中间件测试，linux测试，云原生测试，云计算测试等
License: Apache-2.0
Keywords: automation,testing,test,automated-testing,cli,command-line,shell,ssh,configuration,yaml,config,settings,remote-execution,remote-command,ssh-command,ci-cd,continuous-integration,client,development-tools,dev-tools,utility,sysadmin,system-administration,commend,script-execution,shell-script,bash-script
Author: chineseluo
Author-email: 848257135@qq.com
Requires-Python: >=3.9,<4.0
Classifier: License :: OSI Approved :: Apache Software License
Classifier: Programming Language :: Python :: 3
Classifier: Programming Language :: Python :: 3.9
Classifier: Programming Language :: Python :: 3.10
Classifier: Programming Language :: Python :: 3.11
Classifier: Programming Language :: Python :: 3.12
Requires-Dist: argparse (>=1.4.0,<2.0.0)
Requires-Dist: jinja2 (>=3.1.4,<4.0.0)
Requires-Dist: loguru (>=0.7.3,<0.8.0)
Requires-Dist: paramiko (>=3.5.0,<4.0.0)
Requires-Dist: prettytable (>=3.12.0,<4.0.0)
Requires-Dist: pydantic (>=2.10.3,<3.0.0)
Requires-Dist: pyfiglet (>=1.0.2,<2.0.0)
Requires-Dist: pyyaml (>=6.0.2,<7.0.0)
Requires-Dist: termcolor (>=2.5.0,<3.0.0)
